LICENSE
MANIFEST.in
README
README.rst
setup.cfg
setup.py
src/flake8_ownership.py
src/flake8_ownership.egg-info/PKG-INFO
src/flake8_ownership.egg-info/SOURCES.txt
src/flake8_ownership.egg-info/dependency_links.txt
src/flake8_ownership.egg-info/entry_points.txt
src/flake8_ownership.egg-info/not-zip-safe
src/flake8_ownership.egg-info/requires.txt
src/flake8_ownership.egg-info/top_level.txt