Metadata-Version: 1.1
Name: flake8-ownership
Version: 2.0.0
Summary: A flake8 checker for assuring that author, copyright, and license are specified in source files.
Home-page: https://flake8-ownership.readthedocs.io
Author: Joe Joyce
Author-email: joe@decafjoe.com
License: BSD
Platform: UNKNOWN
Classifier: Development Status :: 4 - Beta
Classifier: Framework :: Flake8
Classifier: Intended Audience :: Developers
Classifier: License :: OSI Approved :: BSD License
Classifier: Operating System :: OS Independent
Classifier: Programming Language :: Python :: 2
Classifier: Programming Language :: Python :: 2.7
Classifier: Programming Language :: Python :: 3
Classifier: Programming Language :: Python :: 3.4
Classifier: Programming Language :: Python :: 3.5
Classifier: Programming Language :: Python :: 3.6
Classifier: Programming Language :: Python :: Implementation :: PyPy
